rtl/FLOAT_MUL/FLOAT_MUL.v
//author: Jesse
//module: Double Precision Multiplier
//IEEE754 format
//64bit = 1bit |  11bit   | 52bit
//        Sign | Exponent | Mantissa
module FLOAT_MUL (
    input [(BIT-1):0] num1,
    input [(BIT-1):0] num2,
    input clk,
    input rstn,
    output [(BIT-1):0] result,
    input valid,
    output ready
);
localparam BIT = 64;
localparam BIAS = 1023;
localparam EXPONENT_LEN = 11;
localparam MANTISSA_LEN = 52;


//-----pipeline stage: 0-----//
reg [(BIT-1):0]pip0_num1;
reg [(BIT-1):0]pip0_num2;
reg pip0_valid;
always @(posedge clk or negedge rstn) begin
  if (!rstn) begin
    pip0_num1 <= 0;
    pip0_num2 <= 0;
    pip0_valid <= 0;
  end else begin
    pip0_num1 <= num1;
    pip0_num2 <= num2;
    pip0_valid <= valid;
  end
end
//---------------------------//

//-----pipeline stage: 1-----//
//this stage is input buffer
reg pip1_sign1;
reg pip1_sign2;
reg pip1_valid;
reg [(EXPONENT_LEN-1):0] pip1_exponent1;
reg [(EXPONENT_LEN-1):0] pip1_exponent2;
reg pip1_zero;
wire zero;
wire num1_zero;
wire num2_zero;
wire check_denor1;
wire check_denor2;
always @(posedge clk or negedge rstn) begin
    if (!rstn) begin
      pip1_sign1 <= 0;
      pip1_sign2 <= 0;
      pip1_valid <= 0;
      pip1_exponent1 <= 0;
      pip1_exponent2 <= 0;
      pip1_zero <= 0;
    end else begin
      pip1_sign1 <= pip0_num1[63];
      pip1_sign2 <= pip0_num2[63];
      pip1_valid <= pip0_valid;
      if (check_denor1) begin   //for denormalize number
        pip1_exponent1 <= 11'd1; //1-BIAS = -1022
      end else begin
        pip1_exponent1 <= pip0_num1[62:52];
      end
      if (check_denor2) begin   //for denormalize number
        pip1_exponent2 <= 11'd1;  //1-BIAS = -1022
      end else begin
        pip1_exponent2 <= pip0_num2[62:52];
      end
      pip1_zero <= zero;
    end
end
assign zero = (num1_zero | num2_zero); //check zero
assign num1_zero = ~(|pip0_num1[62:0]); //check pip0_num1 zero
assign num2_zero = ~(|pip0_num2[62:0]); //check pip0_num2 zero
assign check_denor1 = ~(|pip0_num1[62:52]); //check denormalize number
assign check_denor2 = ~(|pip0_num2[62:52]); //check denormalize number
//53bit: 1bit(leading 1) + 52bit(mantissa)
reg [(MANTISSA_LEN):0] pip1_mantissa1 [(MANTISSA_LEN):0];
reg [(MANTISSA_LEN):0] pip1_mantissa2;
integer i;
always @(posedge clk or negedge rstn) begin
    if (!rstn) begin
      for (i = 0; i < 53; i=i+1) begin
        pip1_mantissa1[i][(MANTISSA_LEN):0] <= 0;
      end
      pip1_mantissa2[(MANTISSA_LEN):0] <= 0;
    end else begin
      for (i = 0; i <= 52; i=i+1) begin //0~51
        if (check_denor1) begin
          pip1_mantissa1[i][(MANTISSA_LEN):0] <= {1'b0, pip0_num1[51:0]};
        end else begin
          pip1_mantissa1[i][(MANTISSA_LEN):0] <= {1'b1, pip0_num1[51:0]};
        end
      end
      if (check_denor2) begin
        pip1_mantissa2[(MANTISSA_LEN):0] <= {1'b0, pip0_num2[51:0]};
      end else begin
        pip1_mantissa2[(MANTISSA_LEN):0] <= {1'b1, pip0_num2[51:0]};
      end
    end
end
//---------------------------//

//-----pipeline stage: 2-----//
//calculate sign, add exponent, anding num1 and num2
reg pip2_sign;
reg pip2_valid;
//1bit(check overflow) + 11bit(exponent)
reg [(EXPONENT_LEN):0] pip2_exponent;
reg pip2_zero;
always @(posedge clk or negedge rstn) begin
    if (!rstn) begin
      pip2_sign <= 0;
      pip2_exponent <= 0;
      pip2_zero <= 0;
      pip2_valid <= 0;
    end else begin
      pip2_sign <= pip1_sign1 ^ pip1_sign2;
      pip2_exponent <= pip1_exponent1 + pip1_exponent2;
      pip2_zero <= pip1_zero;
      pip2_valid <= pip1_valid;
    end
end
//AND num1 with each bit of num2
reg [(MANTISSA_LEN):0] pip2_mantissa [(MANTISSA_LEN):0];
always @(posedge clk or negedge rstn) begin
    if (!rstn) begin
      for (i = 0; i < 53; i++) begin
        pip2_mantissa [i][(MANTISSA_LEN):0] <= 0;
      end 
    end else begin
      for (i = 0; i < 53; i++) begin
        pip2_mantissa [i][(MANTISSA_LEN):0] <= pip1_mantissa1[i] & {53{pip1_mantissa2[i]}};
      end
    end
end
//---------------------------//

//-----pipeline stage: 3-----//
reg pip3_sign;
reg pip3_valid;
reg [(EXPONENT_LEN):0]pip3_exponent;
always @(posedge clk or negedge rstn) begin
    if (!rstn) begin
      pip3_sign <= 0;
      pip3_exponent <= 0;
      pip3_valid <= 0;
    end else begin
      pip3_valid <= pip2_valid;
      if (pip2_zero) begin
        pip3_exponent <= 0;
        pip3_sign <= 0;
      end else begin
        pip3_exponent <= pip2_exponent - BIAS;
        pip3_sign <= pip2_sign;
      end
    end
end
//55bit = 54bit(pip2_mantissa1 shift 1bit) + 53bit(pip2_mantissa1)
//27number
reg [(MANTISSA_LEN+2):0]pip3_mantissa[(MANTISSA_LEN/2):0];
always @(posedge clk or negedge rstn) begin
    if (!rstn) begin
      for (i = 0; i <= (MANTISSA_LEN/2); i++) begin
        pip3_mantissa[i] <= 0;
      end
    end else begin
      //Group A, B, C
      for (i = 0; i < (MANTISSA_LEN/2); i++) begin
        pip3_mantissa[i] <= pip2_mantissa[2*i] + {pip2_mantissa[2*i+1], 1'b0};
      end
      //Group D
      pip3_mantissa[(MANTISSA_LEN/2)] <= pip2_mantissa[MANTISSA_LEN];
    end
end 
//---------------------------//

//-----pipeline stage: 4-----//
reg pip4_sign;
reg pip4_valid;
reg [(EXPONENT_LEN):0]pip4_exponent;
reg [(MANTISSA_LEN + 4):0]pip4_mantissa[(MANTISSA_LEN/4):0];
always @(posedge clk or negedge rstn) begin
    if (!rstn) begin
      pip4_sign <= 0;
      pip4_valid <= 0;
      pip4_exponent <= 0;
      for (i = 0; i <= (MANTISSA_LEN/4); i++) begin
        pip4_mantissa[i] <= 0;
      end
    end else begin
      pip4_sign <= pip3_sign;
      pip4_valid <= pip3_valid;
      pip4_exponent <= pip3_exponent;
      for (i = 0; i < (MANTISSA_LEN/4); i++) begin
        pip4_mantissa[i] <= pip3_mantissa[2*i] + {pip3_mantissa[2*i+1], 2'b00};
      end
      pip4_mantissa[(MANTISSA_LEN/4)] <= pip3_mantissa[(MANTISSA_LEN/2)];
    end
end
//14number
//---------------------------//

//-----pipeline stage: 5-----//
reg pip5_sign;
reg pip5_valid;
reg [(EXPONENT_LEN):0]pip5_exponent;
reg [(MANTISSA_LEN+8):0]pip5_mantissa[7:0];
always @(posedge clk or negedge rstn) begin
    if (!rstn) begin
      pip5_sign <= 0;
      pip5_valid <= 0;
      pip5_exponent <= 0;
      for (i = 0; i <= 7; i++) begin
        pip5_mantissa[i] <= 0;
      end
    end else begin
      pip5_sign <= pip4_sign;
      pip5_valid <= pip4_valid;
      pip5_exponent <= pip4_exponent;
      for (i = 0; i <= 5; i++) begin
        pip5_mantissa[i] <= pip4_mantissa[2*i] + {pip4_mantissa[2*i+1], 4'b0000};
      end
      pip5_mantissa[6] <= pip4_mantissa[(MANTISSA_LEN/4)-1];
      pip5_mantissa[7] <= pip4_mantissa[(MANTISSA_LEN/4)];
    end
end
//61bit, 8number
//---------------------------//

//-----pipeline stage: 6-----//
reg pip6_sign;
reg pip6_valid;
reg [(EXPONENT_LEN):0]pip6_exponent;
reg [(MANTISSA_LEN+16):0]pip6_mantissa[4:0];
//69bit, 5number
always @(posedge clk or negedge rstn) begin
    if (!rstn) begin
      pip6_sign <= 0;
      pip6_valid <= 0;
      pip6_exponent <= 0;
      for (i = 0; i <= 4; i++) begin
        pip6_mantissa[i] <= 0;
      end
    end else begin
      pip6_sign <= pip5_sign;
      pip6_valid <= pip5_valid;
      pip6_exponent <= pip5_exponent;
      for (i = 0; i <= 2; i++) begin
        pip6_mantissa[i] <= pip5_mantissa[2*i] + {pip5_mantissa[2*i+1], 8'h00};
      end
      pip6_mantissa[3] <= pip5_mantissa[6];
      pip6_mantissa[4] <= pip5_mantissa[7];
    end
end
//---------------------------//

//-----pipeline stage: 7-----//
reg pip7_sign;
reg pip7_valid;
reg [(EXPONENT_LEN):0]pip7_exponent;
reg [(MANTISSA_LEN+32):0]pip7_mantissa[3:0];
//85bit, 4number
always @(posedge clk or negedge rstn) begin
    if (!rstn) begin
      pip7_sign <= 0;
      pip7_valid <= 0;
      pip7_exponent <= 0;
      for (i = 0; i <= 3; i++) begin
        pip7_mantissa[i] <= 0;
      end
    end else begin
      pip7_sign <= pip6_sign;
      pip7_valid <= pip6_valid;
      pip7_exponent <= pip6_exponent;
      //Group A
      pip7_mantissa[0] <= pip6_mantissa[0] + {pip6_mantissa[1], 16'h0000};
      //Group B
      pip7_mantissa[1] <= pip6_mantissa[2];
      //Group C
      pip7_mantissa[2] <= pip6_mantissa[3];
      //Group D
      pip7_mantissa[3] <= pip6_mantissa[4];
    end
end
//---------------------------//

//-----pipeline stage: 8-----//
reg pip8_sign;
reg pip8_valid;
reg [(EXPONENT_LEN):0]pip8_exponent;
reg [31:0] pip8_A_remain;
reg [3:0] pip8_C_remain;
reg [53:0]pip8_w; //1bit(carry) + 53bit
reg [16:0]pip8_x; //1bit(carry) + 16bit
reg [16:0]pip8_y; //1bit(carry) + 16bit
reg [37:0]pip8_z; //1bit(carry) + 37bit

always @(posedge clk or negedge rstn) begin
    if (!rstn) begin
      pip8_sign <= 0;
      pip8_valid <= 0;
      pip8_exponent <= 0;
      pip8_A_remain <= 0;
      pip8_C_remain <= 0;
      pip8_w <= 0;
      pip8_x <= 0;
      pip8_y <= 0;
      pip8_z <= 0;
    end else begin
      pip8_sign <= pip7_sign;
      pip8_valid <= pip7_valid;
      pip8_exponent <= pip7_exponent;
      pip8_A_remain <= pip7_mantissa[0][31:0];
      pip8_C_remain <= pip7_mantissa[2][3:0];
      pip8_w <= pip7_mantissa[0][84:48] + pip7_mantissa[1][68:16];
      pip8_x <= pip7_mantissa[0][47:32] + pip7_mantissa[1][15:0];
      pip8_y <= pip7_mantissa[2][56:41] + pip7_mantissa[3][52:37];
      pip8_z <= pip7_mantissa[2][40:4] + pip7_mantissa[3][36:0];
    end
end
//---------------------------//

//-----pipeline stage: 9-----//
reg pip9_sign;
reg pip9_valid;
reg [(EXPONENT_LEN):0]pip9_exponent;
reg [101:0]pip9_AB;
reg [57:0]pip9_CD;
wire [53:0]pip9_w;
wire [16:0]pip9_y;
assign pip9_w = pip8_w + pip8_x[16];//add carry
assign pip9_y = pip8_y + pip8_z[37];//add carry
always @(posedge clk or negedge rstn) begin
    if (!rstn) begin
      pip9_sign <= 0;
      pip9_valid <= 0;
      pip9_exponent <= 0;
      pip9_AB <= 0;
      pip9_CD <= 0;
    end else begin
      pip9_sign <= pip8_sign;
      pip9_valid <= pip8_valid;
      pip9_exponent <= pip8_exponent;
      pip9_AB <= {pip9_w, pip8_x[15:0], pip8_A_remain};
      pip9_CD <= {pip9_y, pip8_z[36:0], pip8_C_remain};
    end
end
//---------------------------//

//-----pipeline stage: 10----//
reg pip10_sign;
reg pip10_valid;
reg [(EXPONENT_LEN):0]pip10_exponent;
reg [47:0]pip10_AB_remain;
reg [31:0]pip10_n; //32bit = 1bit(carry)+31bit
reg [27:0]pip10_m; //28bit = 1bit(carry)+27bit
always @(posedge clk or negedge rstn) begin
    if (!rstn) begin
      pip10_sign <= 0;
      pip10_valid <= 0;
      pip10_exponent <= 0;
      pip10_AB_remain <= 0;
      pip10_n <= 0;
      pip10_m <= 0;
    end else begin
      pip10_sign <= pip9_sign;
      pip10_valid <= pip9_valid;
      pip10_exponent <= pip9_exponent;
      pip10_AB_remain <= pip9_AB[47:0];
      pip10_n <= pip9_AB[78:48] + pip9_CD[30:0];
      pip10_m <= pip9_AB[101:79] + pip9_CD[57:31];
    end
end
//---------------------------//

//-----pipeline stage: 11----//
reg pip11_sign;
reg pip11_valid;
reg [(EXPONENT_LEN):0]pip11_exponent;
wire [26:0]pip11_mn;//27bit (need 1 bit carry?)
reg [105:0]pip11_mantissa;
assign pip11_mn = pip10_m + pip10_n[31];
always @(posedge clk or negedge rstn) begin
    if (!rstn) begin
      pip11_sign <= 0;
      pip11_valid <= 0;
      pip11_exponent <= 0;
      pip11_mantissa <= 0;
    end else begin
      pip11_sign <= pip10_sign;
      pip11_valid <= pip10_valid;
      pip11_exponent <= pip10_exponent;
      pip11_mantissa <= {pip11_mn, pip10_n[30:0], pip10_AB_remain};
    end
end 
//---------------------------//

//-----pipeline stage: 12----//
reg pip12_sign;
reg pip12_valid;
reg [(EXPONENT_LEN-1):0]pip12_exponent;
reg [105:0]pip12_mantissa;
always @(posedge clk or negedge rstn) begin
    if (!rstn) begin
      pip12_sign <= 0;
      pip12_valid <= 0;
      pip12_exponent <= 0;
      pip12_mantissa <= 0;
    end else begin
      pip12_sign <= pip11_sign;
      pip12_valid <= pip11_valid;
      if (pip11_mantissa[105] == 1'b1) begin //normalize
        pip12_exponent <= pip11_exponent + 1'b1;
        pip12_mantissa <= pip11_mantissa >> 1; //shift right
      end else begin
        pip12_exponent <= pip11_exponent;
        pip12_mantissa <= pip11_mantissa;
      end
    end
end
//---------------------------//

//-----pipeline stage: 13----//
reg pip13_sign;
reg pip13_valid;
assign ready = pip13_valid;
reg [(EXPONENT_LEN-1):0]pip13_exponent;
reg [(MANTISSA_LEN-1):0]pip13_mantissa;
wire LSB = pip12_mantissa[52];
wire Guard = pip12_mantissa[51];
wire Round = pip12_mantissa[50];
wire Sticky = |pip12_mantissa[49:0];
wire round_up = Guard & (Round | Sticky | LSB);
always @(posedge clk or negedge rstn) begin
  if (!rstn) begin
    pip13_sign <= 0;
    pip13_valid <= 0;
    pip13_exponent <= 0;
    pip13_mantissa <= 0;
  end else begin
    pip13_sign <= pip12_sign;
    pip13_valid <= pip12_valid;
    pip13_exponent <= pip12_exponent;
    if (round_up) begin
      pip13_mantissa <= pip12_mantissa[103:52] + 1;
    end else begin
      pip13_mantissa <= pip12_mantissa[103:52];
    end
  end
end
assign result = {pip13_sign, pip13_exponent, pip13_mantissa};
//---------------------------//
endmodule //IEEE754_64bit_mul

rtl/FLOAT_MUL/FLOAT_MUL_tb.v
// Author: Jesse
`timescale 1ns / 1ps
`include "FLOAT_MUL.v"
module FLOAT_MUL_tb ();
localparam BIT = 64;
localparam BIAS = 1023;
localparam EXPONENT_LEN = 11;
localparam MANTISSA_LEN = 52;
localparam N=1000;


reg clk;
reg rstn;
reg [(BIT-1):0]num1;
reg [(BIT-1):0]num2;
wire [63:0]result;
reg valid;
wire ready;

FLOAT_MUL uut(
    .num1(num1),
    .num2(num2),
    .clk(clk),
    .rstn(rstn),
    .result(result),
    .valid(valid),
    .ready(ready)
);
//-----clock generate-----//
initial begin
    clk = 0;
    forever begin
        #5 clk = (~clk);
    end
end
//-----reset-----//
initial begin
    rstn = 0;
    repeat (2) @(posedge clk);
    rstn = 1;
end

// ---------- memory ----------
reg [63:0] num1_mem [0:N-1];
reg [63:0] num2_mem [0:N-1];
reg [63:0] golden_result [0:N-1];

integer fd, i = 0, r;
reg [63:0] t1, t2, t3;

// ---------- file reading ----------
initial begin
    fd = $fopen("./py/golden.dat", "r"); // read("r") golden.dat
    if (!fd) begin
        $display("❌ Error: Cannot open golden.dat");
        $finish;
    end
    //if file is end, $feof will return 1, jump out of loop
    //r represent read how many row from file
    while (!$feof(fd)) begin
        r = $fscanf(fd, "%h %h %h\n", t1, t2, t3);
        if (r == 3) begin
            num1_mem[i] = t1;
            num2_mem[i] = t2;
            golden_result[i] = t3;
            i = i + 1;
        end else begin
            $display("⚠️ Warning: Invalid line format at index %0d", i);
        end
    end
    $fclose(fd);
    $display("✅ Loaded %0d test patterns from golden.dat", i);
end

// ---------- feed input ----------
integer j;
initial begin
    valid = 0;
    wait(rstn == 1);
    for (j = 0; j < i; j = j + 1) begin
        @(negedge clk);
        valid <= 1;
        num1 <= num1_mem[j];
        num2 <= num2_mem[j];
    end
    // flush
    @(negedge clk);
    valid <= 0;
    num1 <= 0;
    num2 <= 0;
end

//-----prevent hang
integer timeout = (100000);
initial begin
    while(timeout > 0) begin
        @(posedge clk);
        timeout = timeout - 1;
    end
    $display($time, "Simualtion Hang ....");
    $finish;
end

// ---------- check result ----------
integer k = 0;
integer errors = 0;
initial begin
    wait(rstn == 1);
    repeat(14) @(posedge clk); // 等待 pipeline 開始輸出

    while (k < N) begin
        @(posedge clk);
        if (result != golden_result[k]) begin
          $display("❌ [Mismatch] Pattern %0d: result = %h, expected = %h",
                    k , result, golden_result[k]);
                errors = errors + 1;
        end else begin
          $display("✅ [Match] Pattern %0d: result = %h, expected = %h", k, result, golden_result[k]);
        end
        k = k + 1;
    end

    $display("🎯 Test completed: %0d errors out of %0d patterns", errors, i);
    if (errors == 0)
        $display("🎉 ALL PASS!");
    else
        $display("⚠️ Some mismatches found. Please check your design.");
    repeat (10) @(posedge clk);
    $finish;
end

initial begin
    $dumpfile("mul.vcd");
    $dumpvars();
    //$dumpvars(0, uut.pip1_mantissa1[52]);
    //$dumpvars(0, uut.pip1_mantissa1[2]);
    //$dumpvars(0, uut.pip1_mantissa1[1]);
end


endmodule //IEEE754_64bit_mul_tb

rtl/FLOAT_MUL/mul.vcd
$date
	Sat May 24 11:25:55 2025
$end
$version
	Icarus Verilog
$end
$timescale
	1ps
$end
$scope module FLOAT_MUL_tb $end
$var wire 64 ! result [63:0] $end
$var wire 1 " ready $end
$var reg 1 # clk $end
$var reg 64 $ num1 [63:0] $end
$var reg 64 % num2 [63:0] $end
$var reg 1 & rstn $end
$var reg 64 ' t1 [63:0] $end
$var reg 64 ( t2 [63:0] $end
$var reg 64 ) t3 [63:0] $end
$var reg 1 * valid $end
$var integer 32 + errors [31:0] $end
$var integer 32 , fd [31:0] $end
$var integer 32 - i [31:0] $end
$var integer 32 . j [31:0] $end
$var integer 32 / k [31:0] $end
$var integer 32 0 r [31:0] $end
$var integer 32 1 timeout [31:0] $end
$scope module uut $end
$var wire 1 2 check_denor1 $end
$var wire 1 3 check_denor2 $end
$var wire 1 # clk $end
$var wire 64 4 num1 [63:0] $end
$var wire 1 5 num1_zero $end
$var wire 64 6 num2 [63:0] $end
$var wire 1 7 num2_zero $end
$var wire 1 " ready $end
$var wire 1 8 round_up $end
$var wire 1 & rstn $end
$var wire 1 * valid $end
$var wire 1 9 zero $end
$var wire 64 : result [63:0] $end
$var wire 17 ; pip9_y [16:0] $end
$var wire 54 < pip9_w [53:0] $end
$var wire 27 = pip11_mn [26:0] $end
$var wire 1 > Sticky $end
$var wire 1 ? Round $end
$var wire 1 @ LSB $end
$var wire 1 A Guard $end
$var reg 64 B pip0_num1 [63:0] $end
$var reg 64 C pip0_num2 [63:0] $end
$var reg 1 D pip0_valid $end
$var reg 48 E pip10_AB_remain [47:0] $end
$var reg 12 F pip10_exponent [11:0] $end
$var reg 28 G pip10_m [27:0] $end
$var reg 32 H pip10_n [31:0] $end
$var reg 1 I pip10_sign $end
$var reg 1 J pip10_valid $end
$var reg 12 K pip11_exponent [11:0] $end
$var reg 106 L pip11_mantissa [105:0] $end
$var reg 1 M pip11_sign $end
$var reg 1 N pip11_valid $end
$var reg 11 O pip12_exponent [10:0] $end
$var reg 106 P pip12_mantissa [105:0] $end
$var reg 1 Q pip12_sign $end
$var reg 1 R pip12_valid $end
$var reg 11 S pip13_exponent [10:0] $end
$var reg 52 T pip13_mantissa [51:0] $end
$var reg 1 U pip13_sign $end
$var reg 1 V pip13_valid $end
$var reg 11 W pip1_exponent1 [10:0] $end
$var reg 11 X pip1_exponent2 [10:0] $end
$var reg 53 Y pip1_mantissa2 [52:0] $end
$var reg 1 Z pip1_sign1 $end
$var reg 1 [ pip1_sign2 $end
$var reg 1 \ pip1_valid $end
$var reg 1 ] pip1_zero $end
$var reg 12 ^ pip2_exponent [11:0] $end
$var reg 1 _ pip2_sign $end
$var reg 1 ` pip2_valid $end
$var reg 1 a pip2_zero $end
$var reg 12 b pip3_exponent [11:0] $end
$var reg 1 c pip3_sign $end
$var reg 1 d pip3_valid $end
$var reg 12 e pip4_exponent [11:0] $end
$var reg 1 f pip4_sign $end
$var reg 1 g pip4_valid $end
$var reg 12 h pip5_exponent [11:0] $end
$var reg 1 i pip5_sign $end
$var reg 1 j pip5_valid $end
$var reg 12 k pip6_exponent [11:0] $end
$var reg 1 l pip6_sign $end
$var reg 1 m pip6_valid $end
$var reg 12 n pip7_exponent [11:0] $end
$var reg 1 o pip7_sign $end
$var reg 1 p pip7_valid $end
$var reg 32 q pip8_A_remain [31:0] $end
$var reg 4 r pip8_C_remain [3:0] $end
$var reg 12 s pip8_exponent [11:0] $end
$var reg 1 t pip8_sign $end
$var reg 1 u pip8_valid $end
$var reg 54 v pip8_w [53:0] $end
$var reg 17 w pip8_x [16:0] $end
$var reg 17 x pip8_y [16:0] $end
$var reg 38 y pip8_z [37:0] $end
$var reg 102 z pip9_AB [101:0] $end
$var reg 58 { pip9_CD [57:0] $end
$var reg 12 | pip9_exponent [11:0] $end
$var reg 1 } pip9_sign $end
$var reg 1 ~ pip9_valid $end
$var integer 32 !" i [31:0] $end
$upscope $end
$upscope $end
$enddefinitions $end
#0
$dumpvars
b110101 !"
0~
0}
b0 |
b0 {
b0 z
b0 y
b0 x
b0 w
b0 v
0u
0t
b0 s
b0 r
b0 q
0p
0o
b0 n
0m
0l
b0 k
0j
0i
b0 h
0g
0f
b0 e
0d
0c
b0 b
0a
0`
0_
b0 ^
0]
0\
0[
0Z
b0 Y
b0 X
b0 W
0V
0U
b0 T
b0 S
0R
0Q
b0 P
b0 O
0N
0M
b0 L
b0 K
0J
0I
b0 H
b0 G
b0 F
b0 E
0D
b0 C
b0 B
0A
0@
0?
0>
b0 =
b0 <
b0 ;
b0 :
19
08
17
bx 6
15
bx 4
13
12
b11000011010100000 1
b11 0
b0 /
bx .
b1111101000 -
b10000000000000000000000000000011 ,
b0 +
0*
b1101000111110011100010110001110001111001010100100000000100001101 )
b1101000000010110110110010010010010101100101011010111100000001001 (
b100000111001011010111110001011110100110001101011000010010111110 '
0&
bx %
bx $
0#
0"
b0 !
$end
#5000
b100 !"
b11000011010011111 1
1#
#10000
0#
#15000
x9
x7
x3
x5
x2
bx C
bx B
1]
b1 X
b1 W
b110000000001 b
b0 .
b110101 !"
b11000011010011110 1
1&
1#
#20000
b100001011010000110010010100010101000110010101111111100110000011 %
b100001011010000110010010100010101000110010101111111100110000011 6
b1100101010010110010111000001000110001111001011010110100100101000 $
b1100101010010110010111000001000110001111001011010110100100101000 4
1*
b1 .
0#
#25000
09
07
03
05
02
b110000000001 e
1a
b10 ^
b1xxxxxxxxxxxxxxxxxxxxxxxxxxxxxxxxxxxxxxxxxxxxxxxxxxxx Y
x]
bx X
bx W
x[
xZ
1D
b100001011010000110010010100010101000110010101111111100110000011 C
b1100101010010110010111000001000110001111001011010110100100101000 B
b11 !"
b11000011010011101 1
1#
#30000
b11011110010110010011001000011110010101011001110000010011011101 %
b11011110010110010011001000011110010101011001110000010011011101 6
b1100110011000010110110111000101011000001011110100101111000111000 $
b1100110011000010110110111000101011000001011110100101111000111000 4
b10 .
0#
#35000
b11011110010110010011001000011110010101011001110000010011011101 C
b1100110011000010110110111000101011000001011110100101111000111000 B
0]
b10000101101 X
b10010101001 W
1\
0[
1Z
b10000110010010100010101000110010101111111100110000011 Y
xa
bx ^
x_
b0 b
b110000000001 h
b110101 !"
b11000011010011100 1
1#
#40000
b11010011100010000110011000011110101011010111101101001111000001 %
b11010011100010000110011000011110101011010111101101001111000001 6
b100000101011110110111101011101111101100100100000010100111110110 $
b100000101011110110111101011101111101100100100000010100111110110 4
b11 .
0#
#45000
b110000000001 k
b0 e
xc
bx b
1`
0a
b100011010110 ^
1_
b10110010011001000011110010101011001110000010011011101 Y
b1101111001 X
b10011001100 W
b11010011100010000110011000011110101011010111101101001111000001 C
b100000101011110110111101011101111101100100100000010100111110110 B
b11 !"
b11000011010011011 1
1#
#50000
b100110011101101011010111010011100000101111110101001111011000010 %
b100110011101101011010111010011100000101111110101001111011000010 6
b10111101010000101111101000011000101110001111001010001010011010 $
b10111101010000101111101000011000101110001111001010001010011010 4
b100 .
0#
#55000
b100110011101101011010111010011100000101111110101001111011000010 C
b10111101010000101111101000011000101110001111001010001010011010 B
b1101001110 X
b10000010101 W
0Z
b10010000110011000011110101011010111101101001111000001 Y
b100001000101 ^
1c
b10011010111 b
1d
bx e
xf
b0 h
b110000000001 n
b110101 !"
b11000011010011010 1
1#
#60000
b11001010111010010100001101000101111110110011111100111110000111 %
b11001010111010010100001101000101111110110011111100111110000111 6
b11010111011011000111010111000001110011011100010111000001011100 $
b11010111011011000111010111000001110011011100010111000001011100 4
b101 .
0#
#65000
b110000000001 s
b0 k
bx h
xi
b10011010111 e
1g
1f
b10001000110 b
b11101100011 ^
0_
b11101011010111010011100000101111110101001111011000010 Y
b10011001110 X
b1011110101 W
b11001010111010010100001101000101111110110011111100111110000111 C
b11010111011011000111010111000001110011011100010111000001011100 B
b11 !"
b11000011010011001 1
1#
#70000
b11011011111011111101110100011010110110011010010111000110000001 %
b11011011111011111101110100011010110110011010010111000110000001 6
b1100001100000001011011000111111010011011111000000011011011001001 $
b1100001100000001011011000111111010011011111000000011011011001001 4
b110 .
0#
#75000
b11011011111011111101110100011010110110011010010111000110000001 C
b1100001100000001011011000111111010011011111000000011011011001001 B
b1100101011 X
b1101011101 W
b11010010100001101000101111110110011111100111110000111 Y
b11111000011 ^
0c
b1101100100 b
b10001000110 e
b10011010111 h
1j
1i
bx k
xl
b0 n
b110000000001 |
b110101 !"
b11000011010011000 1
1#
#80000
b11001111101010101101100110000010110101101001010010011110011110 %
b11001111101010101101100110000010110101101001010010011110011110 6
b1010110011111000010011110100100100000101100010101100100010101011 $
b1010110011111000010011110100100100000101100010101100100010101011 4
b111 .
0#
#85000
b110000000001 F
b0 s
bx n
xo
b10011010111 k
1m
1l
b10001000110 h
b1101100100 e
0f
b1111000100 b
b11010001000 ^
b11011111101110100011010110110011010010111000110000001 Y
b1101101111 X
b10000110000 W
1Z
b11001111101010101101100110000010110101101001010010011110011110 C
b1010110011111000010011110100100100000101100010101100100010101011 B
b11 !"
b11000011010010111 1
1#
#90000
b1100110101101100000111110100011110101010000000110111100100000110 %
b1100110101101100000111110100011110101010000000110111100100000110 6
b100010100000001100000110011111011101110000001110001011101100001 $
b100010100000001100000110011111011101110000001110001011101100001 4
b1000 .
0#
#95000
b1100110101101100000111110100011110101010000000110111100100000110 C
b100010100000001100000110011111011101110000001110001011101100001 B
b1100111110 X
b1011001111 W
b11010101101100110000010110101101001010010011110011110 Y
b11110011111 ^
1_
b1010001001 b
b1111000100 e
b1101100100 h
0i
b10001000110 k
b10011010111 n
1p
1o
bx y
bx ;
bx x
bx w
bx <
bx v
bx r
bx q
bx s
xt
b0 |
b110000000001 K
b110101 !"
b11000011010010110 1
1#
#100000
b100110011000010110011110010111111011101101100111001111000000011 %
b100110011000010110011110010111111011101101100111001111000000011 6
b1011000000100000100110010011101101000111010100001101010100111011 $
b1011000000100000100110010011101101000111010100001101010100111011 4
b1001 .
0#
#105000
b1011001011100000 ;
b10001100101000101011010111111000000100010000011101010 <
b10000000001 O
b0 F
bx {
bx z
bx |
x}
b1000110001111001011010110100100101000 y
b1011001011100000 x
b10000010000110111 w
b10001100101000101011010111111000000100010000011101001 v
b0 r
b11100000111001011011101111000 q
b10011010111 s
1u
1t
b10001000110 n
b1101100100 k
0l
b1111000100 h
b1010001001 e
1c
b1110100000 b
b11000001101 ^
b11100000111110100011110101010000000110111100100000110 Y
b10011010110 X
b10001010000 W
1[
0Z
b100110011000010110011110010111111011101101100111001111000000011 C
b1011000000100000100110010011101101000111010100001101010100111011 B
b11 !"
b11000011010010101 1
1#
#110000
b11001101001010100011101000011101101010010101000010100001100110 %
b11001101001010100011101000011101101010010101000010100001100110 6
b1011101010101100000011010001000000110100000001010110011111110100 $
b1011101010101100000011010001000000110100000001010110011111110100 4
b1010 .
0#
#115000
bx =
b11001101001010100011101000011101101010010101000010100001100110 C
b1011101010101100000011010001000000110100000001010110011111110100 B
b10011001100 X
b1100000010 W
0[
1Z
b10010110011110010111111011101101100111001111000000011 Y
b100100100110 ^
b1000001110 b
b1110100000 e
1f
b1010001001 h
b1111000100 k
b1101100100 n
0o
b1111011001010000010000100000110001101 y
b1100111101101110 ;
b1100111101101110 x
b10001001001101001 w
b101101000110010100111111000111110101100111010100110 <
b101101000110010100111111000111110101100111010100101 v
b1110000101001000011011001011000 q
b10001000110 s
b101100101110000010001100011110010110101101001001010000000 {
b10001100101000101011010111111000000100010000011101010000001000011011100011100000111001011011101111000 z
b10011010111 |
1~
1}
bx G
bx H
bx E
bx F
xI
b0 K
b100000000010000000000000000000000000000000000000000000000000000 !
b100000000010000000000000000000000000000000000000000000000000000 :
b10000000001 S
b110101 !"
b11000011010010100 1
1#
#120000
b1100110110010010110101100111110001000100011100011110110001011110 %
b1100110110010010110101100111110001000100011100011110110001011110 6
b1100110111111001111111010111010000110011001011001100010110111010 $
b1100110111111001111111010111010000110011001011001100010110111010 4
b1011 .
0#
